formant/__init__.py
formant/protos/__init__.py
formant/protos/agent/__init__.py
formant/protos/agent/v1/__init__.py
formant/protos/agent/v1/agent_pb2.py
formant/protos/agent/v1/agent_pb2_grpc.py
formant/protos/model/__init__.py
formant/protos/model/v1/__init__.py
formant/protos/model/v1/commands_pb2.py
formant/protos/model/v1/commands_pb2_grpc.py
formant/protos/model/v1/config_pb2.py
formant/protos/model/v1/config_pb2_grpc.py
formant/protos/model/v1/datapoint_pb2.py
formant/protos/model/v1/datapoint_pb2_grpc.py
formant/protos/model/v1/event_pb2.py
formant/protos/model/v1/event_pb2_grpc.py
formant/protos/model/v1/file_pb2.py
formant/protos/model/v1/file_pb2_grpc.py
formant/protos/model/v1/health_pb2.py
formant/protos/model/v1/health_pb2_grpc.py
formant/protos/model/v1/intervention_pb2.py
formant/protos/model/v1/intervention_pb2_grpc.py
formant/protos/model/v1/math_pb2.py
formant/protos/model/v1/math_pb2_grpc.py
formant/protos/model/v1/media_pb2.py
formant/protos/model/v1/media_pb2_grpc.py
formant/protos/model/v1/navigation_pb2.py
formant/protos/model/v1/navigation_pb2_grpc.py
formant/protos/model/v1/ros_pb2.py
formant/protos/model/v1/ros_pb2_grpc.py
formant/protos/model/v1/text_pb2.py
formant/protos/model/v1/text_pb2_grpc.py
formant/protos/model/v1/views_pb2.py
formant/protos/model/v1/views_pb2_grpc.py
formant/protos/protoc_gen_swagger/__init__.py
formant/protos/protoc_gen_swagger/v1/__init__.py
formant/sdk/__init__.py
formant/sdk/agent/__init__.py
formant/sdk/agent/adapter_utils/__init__.py
formant/sdk/agent/adapter_utils/json_schema_validator.py
formant/sdk/agent/v1/__init__.py
formant/sdk/agent/v1/cancellable_stream_thread.py
formant/sdk/agent/v1/client.py
formant/sdk/agent/v1/exceptions.py
formant/sdk/agent/v1/localization/__init__.py
formant/sdk/agent/v1/localization/localization_manager.py
formant/sdk/agent/v1/localization/utils.py
formant/sdk/agent/v1/localization/types/__init__.py
formant/sdk/agent/v1/localization/types/goal.py
formant-1.324.0.dist-info/METADATA
formant-1.324.0.dist-info/WHEEL
formant-1.324.0.dist-info/top_level.txt
formant-1.324.0.dist-info/RECORD
