Metadata-Version: 2.4
Name: formant
Version: 1.324.0
Summary: Formant python package (Python 3.12)
Home-page: https://formant.io
Author: Formant
Author-email: eng@formant.io
License: MIT
Classifier: Programming Language :: Python :: 3.12
Classifier: License :: OSI Approved :: MIT License
Classifier: Operating System :: OS Independent
Requires-Python: >=2.7,<4
Requires-Dist: typing-extensions>=3.7.4.2
Requires-Dist: requests>=2.25.1
Requires-Dist: python-lzf>=0.2.4
Requires-Dist: jsonschema>=1.0.0
Requires-Dist: python-dateutil
Requires-Dist: httpx<0.24.0,>=0.15.4
Requires-Dist: numpy>=1.16.6
Requires-Dist: wheel>=0.37.1
Requires-Dist: grpcio==1.60.1; python_version >= "3.12"
Requires-Dist: grpcio-status==1.60.1; python_version >= "3.12"
Requires-Dist: googleapis-common-protos>=1.60.0; python_version >= "3.12"
Requires-Dist: protobuf==4.21.12; python_version >= "3.12"
Dynamic: author
Dynamic: author-email
Dynamic: classifier
Dynamic: description
Dynamic: description-content-type
Dynamic: home-page
Dynamic: license
Dynamic: requires-dist
Dynamic: requires-python
Dynamic: summary
